autokakao/__init__.py
autokakao/applescript.py
autokakao/utils.py
autokakao/wrapper.py
autokakao-0.0.3.dist-info/LICENSE
autokakao-0.0.3.dist-info/METADATA
autokakao-0.0.3.dist-info/WHEEL
autokakao-0.0.3.dist-info/top_level.txt
autokakao-0.0.3.dist-info/RECORD
