Metadata-Version: 2.1
Name: autokakao
Version: 0.0.3
Summary: A Simple Kakaotalk Automation Wrapper.
Home-page: https://github.com/yoonhero/autokakao
Author: Yoonhero
Author-email: yoonhero06@naver.com
License: UNKNOWN
Platform: UNKNOWN
Classifier: Programming Language :: Python :: 3
Classifier: License :: OSI Approved :: MIT License
Classifier: Operating System :: OS Independent
Requires-Python: >=3.6
License-File: LICENSE
